odoo8_addon_quality_control_mrp-8.0.1.0.0.99.dev36-py3.8-nspkg.pth
odoo_addons/quality_control_mrp/README.rst
odoo_addons/quality_control_mrp/__init__.py
odoo_addons/quality_control_mrp/__openerp__.py
odoo_addons/quality_control_mrp/data/quality_control_mrp_data.xml
odoo_addons/quality_control_mrp/i18n/ca.po
odoo_addons/quality_control_mrp/i18n/de.po
odoo_addons/quality_control_mrp/i18n/el_GR.po
odoo_addons/quality_control_mrp/i18n/es.po
odoo_addons/quality_control_mrp/i18n/es_ES.po
odoo_addons/quality_control_mrp/i18n/es_MX.po
odoo_addons/quality_control_mrp/i18n/eu.po
odoo_addons/quality_control_mrp/i18n/fi.po
odoo_addons/quality_control_mrp/i18n/fr.po
odoo_addons/quality_control_mrp/i18n/fr_CH.po
odoo_addons/quality_control_mrp/i18n/fr_FR.po
odoo_addons/quality_control_mrp/i18n/gl.po
odoo_addons/quality_control_mrp/i18n/hr.po
odoo_addons/quality_control_mrp/i18n/hr_HR.po
odoo_addons/quality_control_mrp/i18n/it.po
odoo_addons/quality_control_mrp/i18n/nl.po
odoo_addons/quality_control_mrp/i18n/nl_NL.po
odoo_addons/quality_control_mrp/i18n/pt.po
odoo_addons/quality_control_mrp/i18n/pt_BR.po
odoo_addons/quality_control_mrp/i18n/quality_control_mrp.pot
odoo_addons/quality_control_mrp/i18n/ro.po
odoo_addons/quality_control_mrp/i18n/ru.po
odoo_addons/quality_control_mrp/i18n/sk.po
odoo_addons/quality_control_mrp/i18n/sl.po
odoo_addons/quality_control_mrp/i18n/tr.po
odoo_addons/quality_control_mrp/i18n/tr_TR.po
odoo_addons/quality_control_mrp/i18n/vi_VN.po
odoo_addons/quality_control_mrp/i18n/zh_CN.po
odoo_addons/quality_control_mrp/models/__init__.py
odoo_addons/quality_control_mrp/models/mrp_production.py
odoo_addons/quality_control_mrp/models/qc_inspection.py
odoo_addons/quality_control_mrp/static/description/icon.png
odoo_addons/quality_control_mrp/tests/__init__.py
odoo_addons/quality_control_mrp/tests/test_quality_control_mrp.py
odoo_addons/quality_control_mrp/views/mrp_production_view.xml
odoo_addons/quality_control_mrp/views/qc_inspection_view.xml
odoo8_addon_quality_control_mrp-8.0.1.0.0.99.dev36.dist-info/METADATA
odoo8_addon_quality_control_mrp-8.0.1.0.0.99.dev36.dist-info/WHEEL
odoo8_addon_quality_control_mrp-8.0.1.0.0.99.dev36.dist-info/namespace_packages.txt
odoo8_addon_quality_control_mrp-8.0.1.0.0.99.dev36.dist-info/top_level.txt
odoo8_addon_quality_control_mrp-8.0.1.0.0.99.dev36.dist-info/RECORD
